Metadata-Version: 2.1
Name: fastapi-openapi-generator
Version: 0.1.4
Summary: A Command Line Interface to save openapi file from a FastAPI application
Home-page: https://github.com/KiraPC/fastapi-openapi-generator
Author: Pasquale Carmine Carbone
Author-email: pasqualecarmine.carbone@gmail.com
License: UNKNOWN
Platform: UNKNOWN
Classifier: Programming Language :: Python :: 3
Classifier: License :: OSI Approved :: MIT License
Classifier: Operating System :: OS Independent
Requires-Python: >=3.0
